ezgpg
setup.cfg
setup.py
ez_gpg/__init__.py
ez_gpg/config.py
ez_gpg/gpg_utils.py
ez_gpg/ui.py
ez_gpg/ui_utils.py
ez_gpg/data/__init_.py
ez_gpg/data/__init__.py
ez_gpg/data/application.css
ez_gpg/data/decrypt_window.ui
ez_gpg/data/encrypt_window.ui
ez_gpg/data/key_management.ui
ez_gpg/data/main_window.ui
ez_gpg/data/sign_window.ui
ez_gpg/data/verify_window.ui
ezgpg.egg-info/PKG-INFO
ezgpg.egg-info/SOURCES.txt
ezgpg.egg-info/dependency_links.txt
ezgpg.egg-info/entry_points.txt
ezgpg.egg-info/requires.txt
ezgpg.egg-info/top_level.txt
ezgpg.egg-info/zip-safe