Metadata-Version: 1.1
Name: ezgpg
Version: 0.2.4
Summary: Simplified GPG UI
Home-page: https://github.com/sgnn7/ez_gpg
Author: Srdjan Grubor
Author-email: sgnn7@sgnn7.org
License: MIT
Keywords: gpg,gpg2,pgp,crypto,cryptography
Platform: UNKNOWN
Classifier: Programming Language :: Python :: 3 :: Only
Classifier: Development Status :: 3 - Alpha
Classifier: Environment :: X11 Applications :: GTK
Classifier: Intended Audience :: End Users/Desktop
Classifier: License :: OSI Approved :: GNU Lesser General Public License v2 (LGPLv2)
Classifier: Operating System :: POSIX :: Linux
Classifier: Natural Language :: English
Classifier: Topic :: Communications :: Email
Classifier: Topic :: Office/Business
Classifier: Topic :: Security :: Cryptography
Classifier: Topic :: Security
Classifier: Topic :: Utilities
